{
    "configurations": [
        {
            "name": "x86-Debug",
            "generator": "Ninja",
            "configurationType": "Debug",
            "inheritEnvironments": [ "msvc_x86" ],
            "buildRoot": "${projectDir}\\Build\\Output\\VisualStudio\\${name}\\Build",
            "installRoot": "${projectDir}\\Build\\Output\\VisualStudio\\${name}\\Install",
            "buildCommandArgs": "-v",
            "ctestCommandArgs": "",
            "variables": [
                {
                    "name": "METHANE_ITT_INSTRUMENTATION_ENABLED",
                    "value": "True",
                    "type": "BOOL"
                },
                {
                    "name": "METHANE_SCOPE_TIMERS_ENABLED",
                    "value": "True",
                    "type": "BOOL"
                },
                {
                    "name": "METHANE_SHADERS_CODEVIEW_ENABLED",
                    "value": "True",
                    "type": "BOOL"
                },
                {
                    "name": "METHANE_RUN_TESTS_DURING_BUILD",
                    "value": "False",
                    "type": "BOOL"
                },
                {
                    "name": "METHANE_COMMAND_EXECUTION_LOGGING",
                    "value": "false",
                    "type": "BOOL"
                },
                {
                    "name": "METHANE_USE_OPEN_IMAGE_IO",
                    "value": "false",
                    "type": "BOOL"
                }
            ]
        },
        {
            "name": "x86-Release",
            "generator": "Ninja",
            "configurationType": "RelWithDebInfo",
            "inheritEnvironments": [ "msvc_x86" ],
            "buildRoot": "${projectDir}\\Build\\Output\\VisualStudio\\${name}\\Build",
            "installRoot": "${projectDir}\\Build\\Output\\VisualStudio\\${name}\\Install",
            "buildCommandArgs": "-v",
            "ctestCommandArgs": "",
            "variables": [
                {
                    "name": "METHANE_ITT_INSTRUMENTATION_ENABLED",
                    "value": "True",
                    "type": "BOOL"
                },
                {
                    "name": "METHANE_SCOPE_TIMERS_ENABLED",
                    "value": "True",
                    "type": "BOOL"
                },
                {
                    "name": "METHANE_SHADERS_CODEVIEW_ENABLED",
                    "value": "True",
                    "type": "BOOL"
                },
                {
                    "name": "METHANE_RUN_TESTS_DURING_BUILD",
                    "value": "False",
                    "type": "BOOL"
                },
                {
                    "name": "METHANE_USE_OPEN_IMAGE_IO",
                    "value": "false",
                    "type": "BOOL"
                },
                {
                    "name": "METHANE_COMMAND_EXECUTION_LOGGING",
                    "value": "false",
                    "type": "BOOL"
                }
            ]
        },
        {
            "name": "x64-Debug",
            "generator": "Ninja",
            "configurationType": "Debug",
            "inheritEnvironments": [ "msvc_x64_x64" ],
            "buildRoot": "${projectDir}\\Build\\Output\\VisualStudio\\${name}\\Build",
            "installRoot": "${projectDir}\\Build\\Output\\VisualStudio\\${name}\\Install",
            "buildCommandArgs": "-v",
            "ctestCommandArgs": "",
            "variables": [
                {
                    "name": "METHANE_ITT_INSTRUMENTATION_ENABLED",
                    "value": "True",
                    "type": "BOOL"
                },
                {
                    "name": "METHANE_SCOPE_TIMERS_ENABLED",
                    "value": "True",
                    "type": "BOOL"
                },
                {
                    "name": "METHANE_SHADERS_CODEVIEW_ENABLED",
                    "value": "True",
                    "type": "BOOL"
                },
                {
                    "name": "METHANE_RUN_TESTS_DURING_BUILD",
                    "value": "False",
                    "type": "BOOL"
                },
                {
                    "name": "METHANE_COMMAND_EXECUTION_LOGGING",
                    "value": "false",
                    "type": "BOOL"
                },
                {
                    "name": "METHANE_USE_OPEN_IMAGE_IO",
                    "value": "false",
                    "type": "BOOL"
                }
            ]
        },
        {
            "name": "x64-Release",
            "generator": "Ninja",
            "configurationType": "RelWithDebInfo",
            "inheritEnvironments": [ "msvc_x64_x64" ],
            "buildRoot": "${projectDir}\\Build\\Output\\VisualStudio\\${name}\\Build",
            "installRoot": "${projectDir}\\Build\\Output\\VisualStudio\\${name}\\Install",
            "buildCommandArgs": "-v",
            "ctestCommandArgs": "",
            "variables": [
                {
                    "name": "METHANE_ITT_INSTRUMENTATION_ENABLED",
                    "value": "True",
                    "type": "BOOL"
                },
                {
                    "name": "METHANE_SCOPE_TIMERS_ENABLED",
                    "value": "True",
                    "type": "BOOL"
                },
                {
                    "name": "METHANE_SHADERS_CODEVIEW_ENABLED",
                    "value": "True",
                    "type": "BOOL"
                },
                {
                    "name": "METHANE_RUN_TESTS_DURING_BUILD",
                    "value": "False",
                    "type": "BOOL"
                },
                {
                    "name": "METHANE_COMMAND_EXECUTION_LOGGING",
                    "value": "False",
                    "type": "BOOL"
                },
                {
                    "name": "METHANE_USE_OPEN_IMAGE_IO",
                    "value": "false",
                    "type": "BOOL"
                }
            ]
        },
        {
            "name": "Linux-Debug",
            "generator": "Unix Makefiles",
            "configurationType": "Debug",
            "buildRoot": "${projectDir}\\Build\\Output\\VisualStudio\\${name}\\Build",
            "installRoot": "${projectDir}\\Build\\Output\\VisualStudio\\${name}\\Install",
            "cmakeExecutable": "/usr/bin/cmake",
            "remoteCopySourcesExclusionList": [ ".vs", ".git", "Build/Output" ],
            "cmakeCommandArgs": "",
            "buildCommandArgs": "-j 4",
            "ctestCommandArgs": "",
            "inheritEnvironments": [ "linux_x64" ],
            "remoteMachineName": "${defaultRemoteMachineName}",
            "remoteCMakeListsRoot": "$HOME/.vs/${projectDirName}/${workspaceHash}/src",
            "remoteBuildRoot": "$HOME/.vs/${projectDirName}/${workspaceHash}/out/build/${name}",
            "remoteInstallRoot": "$HOME/.vs/${projectDirName}/${workspaceHash}/out/install/${name}",
            "remoteCopySources": true,
            "rsyncCommandArgs": "-t --delete --delete-excluded",
            "remoteCopyBuildOutput": false,
            "remoteCopySourcesMethod": "rsync",
            "addressSanitizerRuntimeFlags": "detect_leaks=0",
            "variables": []
        },
        {
            "name": "Linux-Release",
            "generator": "Unix Makefiles",
            "configurationType": "RelWithDebInfo",
            "buildRoot": "${projectDir}\\Build\\Output\\VisualStudio\\${name}\\Build",
            "installRoot": "${projectDir}\\Build\\Output\\VisualStudio\\${name}\\Install",
            "cmakeExecutable": "/usr/bin/cmake",
            "remoteCopySourcesExclusionList": [ ".vs", ".git", "Build/Output" ],
            "cmakeCommandArgs": "",
            "buildCommandArgs": "-j 4",
            "ctestCommandArgs": "",
            "inheritEnvironments": [ "linux_x64" ],
            "remoteMachineName": "${defaultRemoteMachineName}",
            "remoteCMakeListsRoot": "$HOME/.vs/${projectDirName}/${workspaceHash}/src",
            "remoteBuildRoot": "$HOME/.vs/${projectDirName}/${workspaceHash}/out/build/${name}",
            "remoteInstallRoot": "$HOME/.vs/${projectDirName}/${workspaceHash}/out/install/${name}",
            "remoteCopySources": true,
            "rsyncCommandArgs": "-t --delete --delete-excluded",
            "remoteCopyBuildOutput": false,
            "remoteCopySourcesMethod": "rsync",
            "addressSanitizerRuntimeFlags": "detect_leaks=0",
            "variables": []
        }
    ]
}